oc_ftp_upload_worker/ClientDeliverySender.py
oc_ftp_upload_worker/DeliveryDestinations.py
oc_ftp_upload_worker/__init__.py
oc_ftp_upload_worker/__main__.py
oc_ftp_upload_worker/client_availability_update.py
oc_ftp_upload_worker/fs_clients.py
oc_ftp_upload_worker/ftp_connect.py
oc_ftp_upload_worker/independent_upload.py
oc_ftp_upload_worker/upload_errors.py
oc_ftp_upload_worker/upload_steps.py
oc_ftp_upload_worker/upload_worker.py
oc_ftp_upload_worker/resources/mailer/config.json
oc_ftp_upload_worker-2.1.7.dist-info/licenses/LICENSE
oc_ftp_upload_worker-2.1.7.dist-info/METADATA
oc_ftp_upload_worker-2.1.7.dist-info/WHEEL
oc_ftp_upload_worker-2.1.7.dist-info/top_level.txt
oc_ftp_upload_worker-2.1.7.dist-info/RECORD
