Metadata-Version: 2.4
Name: oc-ftp-upload-worker
Version: 2.1.7
Summary: Delivery upload worker
Requires-Python: >=3.6
License-File: LICENSE
Requires-Dist: oc-cdtapi
Requires-Dist: oc-pyfs
Requires-Dist: oc-mailer
Requires-Dist: oc-delivery-apps
Requires-Dist: oc-orm-initializator
Requires-Dist: oc-dlinterface
Requires-Dist: python-gnupg>=0.4.1
Requires-Dist: packaging
Requires-Dist: pyparsing
Requires-Dist: fs
Requires-Dist: pyyaml
Requires-Dist: oc-cdt-queue2>=4.0.1
Requires-Dist: oc-logging
Dynamic: description-content-type
Dynamic: license-file
Dynamic: requires-dist
Dynamic: requires-python
Dynamic: summary
